{"nome":"ADM","alunos":[{"id":1,"senha":"adrian","login":"adrian","cpf":"07653511619","nome":"Adrian","telefone":"32998040251","tipoUsuario":0},{"id":2,"senha":"mario","login":"mario","cpf":"05784741258","nome":"mario","telefone":"358874125747","tipoUsuario":0},{"id":3,"senha":"andre","login":"andre","cpf":"02258744125","nome":"andre","telefone":"3547412587","tipoUsuario":0}],"professor":{"id":1,"senha":"gleiph","login":"glieph","cpf":"05587884511","nome":"gleiph","telefone":"32558741254","tipoUsuario":1},"disciplina":{"nome":"Orientação objetos","sala":"A3012"},"maxAlunos":35}
{"nome":"OO","alunos":[{"id":1,"senha":"adrian","login":"adrian","cpf":"07653511619","nome":"Adrian","telefone":"32998040251","tipoUsuario":0},{"id":2,"senha":"mario","login":"mario","cpf":"05784741258","nome":"mario","telefone":"358874125747","tipoUsuario":0},{"id":3,"senha":"andre","login":"andre","cpf":"02258744125","nome":"andre","telefone":"3547412587","tipoUsuario":0}],"professor":{"id":1,"senha":"gleiph","login":"glieph","cpf":"05587884511","nome":"gleiph","telefone":"32558741254","tipoUsuario":1},"disciplina":{"nome":"Orientação objetos","sala":"A3012"},"maxAlunos":35}
{"nome":"MODELAGEM","alunos":[{"id":1,"senha":"adrian","login":"adrian","cpf":"07653511619","nome":"Adrian","telefone":"32998040251","tipoUsuario":0},{"id":2,"senha":"mario","login":"mario","cpf":"05784741258","nome":"mario","telefone":"358874125747","tipoUsuario":0},{"id":3,"senha":"andre","login":"andre","cpf":"02258744125","nome":"andre","telefone":"3547412587","tipoUsuario":0}],"professor":{"id":1,"senha":"gleiph","login":"glieph","cpf":"05587884511","nome":"gleiph","telefone":"32558741254","tipoUsuario":1},"disciplina":{"nome":"Orientação objetos","sala":"A3012"},"maxAlunos":35}
{"nome":"MODELAGEM","alunos":[{"id":1,"senha":"adrian","login":"adrian","cpf":"07653511619","nome":"Adrian","telefone":"32998040251","tipoUsuario":0},{"id":2,"senha":"mario","login":"mario","cpf":"05784741258","nome":"mario","telefone":"358874125747","tipoUsuario":0},{"id":3,"senha":"andre","login":"andre","cpf":"02258744125","nome":"andre","telefone":"3547412587","tipoUsuario":0}],"professor":{"id":1,"senha":"gleiph","login":"glieph","cpf":"05587884511","nome":"gleiph","telefone":"32558741254","tipoUsuario":1},"disciplina":{"nome":"Orientação objetos","sala":"A3012"},"maxAlunos":35}
